qnt_funcs/__init__.py
qnt_funcs/decoher.py
qnt_funcs/wave_get.py
qnt_funcs/wavestate.py
qnt_funcs-0.1.2.dist-info/METADATA
qnt_funcs-0.1.2.dist-info/WHEEL
qnt_funcs-0.1.2.dist-info/top_level.txt
qnt_funcs-0.1.2.dist-info/RECORD
