Metadata-Version: 2.4
Name: qnt_funcs
Version: 0.1.2
Summary: Advanced tools for Python error handling and syntax correction
Home-page: https://github.com/mi-rivan/qnt_funcs.git
Author: Mozahidul Islam
Author-email: mirivan722@gmail.com
Keywords: error handling,syntax correction,debugging,development tools
Classifier: Programming Language :: Python :: 3
Classifier: License :: OSI Approved :: MIT License
Classifier: Operating System :: OS Independent
Classifier: Development Status :: 4 - Beta
Classifier: Intended Audience :: Developers
Classifier: Topic :: Software Development :: Debuggers
Classifier: Topic :: Software Development :: Libraries :: Python Modules
Requires-Python: >=3.6
Dynamic: author
Dynamic: author-email
Dynamic: classifier
Dynamic: description
Dynamic: description-content-type
Dynamic: home-page
Dynamic: keywords
Dynamic: requires-python
Dynamic: summary
